{
  "cards": [
    {
      "id": "1",
      "imagem": "./assets/image 1.png",
      "produto": "StormTropper",
      "preco": "60.00"
    },
    {
      "id": "2",
      "imagem": "./assets/image 2.png",
      "produto": "Game Boy Classic",
      "preco": "60.00"
    },
    {
      "id": "3",
      "imagem": "./assets/image 1.png",
      "produto": "StormTropper",
      "preco": "60.00"
    },
    {
      "id": "4",
      "imagem": "./assets/image 2.png",
      "produto": "Game Boy Classic",
      "preco": "60.00"
    },
    {
      "id": "5",
      "imagem": "./assets/image 1.png",
      "produto": "StormTropper",
      "preco": "60.00"
    },
    {
      "id": "6",
      "imagem": "./assets/image 2.png",
      "produto": "Game Boy Classic",
      "preco": "60.00"
    },
    {
      "id": "7",
      "imagem": "./assets/image 1.png",
      "produto": "StormTropper",
      "preco": "60.00"
    },
    {
        "id": "6",
        "imagem": "./assets/image 2.png",
        "produto": "Game Boy Classic",
        "preco": "60.00"
      },
      {
        "id": "7",
        "imagem": "./assets/image 1.png",
        "produto": "StormTropper",
        "preco": "60.00"
      }
  ]
}